minionize/__init__.py
minionize/cli.py
minionize/env.py
minionize/execo.py
minionize/file.py
minionize/google.py
minionize/pulsar.py
minionize/reporter/__init__.py
minionize/tests/functionnal/pulsar/publish.py
minionize/tests/unit/__init__.py
minionize/tests/unit/test_cli.py
minionize/tests/unit/test_minionize.py
minionize/types.py
minionize-0.3.4.dist-info/entry_points.txt
minionize-0.3.4.dist-info/LICENSE
minionize-0.3.4.dist-info/WHEEL
minionize-0.3.4.dist-info/METADATA
minionize-0.3.4.dist-info/RECORD
