Metadata-Version: 2.1
Name: minionize
Version: 0.3.4
Summary: Massively Parallel operations made easy
Home-page: https://gitlab.inria.fr/msimonin/minionize
Keywords: experimentation,oar,grid5000,igrida,parallel
Author: msimonin
Author-email: matthieu.simonin@inria.fr
Requires-Python: >=3.6.1,<4.0.0
Classifier: Programming Language :: Python :: 3
Classifier: Programming Language :: Python :: 3.7
Classifier: Programming Language :: Python :: 3.8
Provides-Extra: execo
Provides-Extra: google
Provides-Extra: pulsar
Requires-Dist: asciichartpy (>=1.5.25,<2.0.0)
Requires-Dist: docker (>=4.4.0,<5.0.0)
Requires-Dist: execo (>=2.6.4,<3.0.0); extra == "execo"
Requires-Dist: google-cloud-pubsub (>=2.0.0,<3.0.0); extra == "google"
Requires-Dist: humanize (>=3.0.1,<4.0.0)
Requires-Dist: pandas (>=1.1.3,<2.0.0)
Requires-Dist: pulsar-client (>=2.6.1,<3.0.0); extra == "pulsar"
Requires-Dist: python-dotenv (>=0.14.0,<0.15.0)
Requires-Dist: tox (>=3.20.0,<4.0.0)
Project-URL: Repository, https://gitlab.inria.fr/msimonin/minionize
